nagcat/__init__.py
nagcat/__main__.py
nagcat/config.py
nagcat/nagcat.py
nagcat-1.0.0.data/scripts/nagcat.tmux
nagcat-1.0.0.dist-info/AUTHORS
nagcat-1.0.0.dist-info/LICENSE
nagcat-1.0.0.dist-info/METADATA
nagcat-1.0.0.dist-info/WHEEL
nagcat-1.0.0.dist-info/entry_points.txt
nagcat-1.0.0.dist-info/top_level.txt
nagcat-1.0.0.dist-info/RECORD
