Metadata-Version: 2.1
Name: nagcat
Version: 1.0.0
Summary: A helpful cat which nags you from within the tmux statusbar... because she loves you! =^.^=
Home-page: https://github.com/tassaron/nagcat
Author: Brianna Rainey <brianna@rainey.tech>
License: UNKNOWN
Keywords: reminder,cat
Platform: UNKNOWN
Classifier: Development Status :: 3 - Alpha
Classifier: Programming Language :: Python :: 3 :: Only
License-File: LICENSE
License-File: AUTHORS
